pystatslib/__init__.py
pystatslib/continuous.py
pystatslib/discrete.py
pystatslib/integration.py
pystatslib/regression.py
pystatslib-0.1.0.dist-info/METADATA
pystatslib-0.1.0.dist-info/WHEEL
pystatslib-0.1.0.dist-info/top_level.txt
pystatslib-0.1.0.dist-info/RECORD
